complexnn/__init__.py
complexnn/bn.py
complexnn/conv.py
complexnn/dense.py
complexnn/fft.py
complexnn/init.py
complexnn/norm.py
complexnn/pool.py
complexnn/utils.py
keras_complex-0.2.3.dist-info/LICENSE.md
keras_complex-0.2.3.dist-info/METADATA
keras_complex-0.2.3.dist-info/WHEEL
keras_complex-0.2.3.dist-info/top_level.txt
keras_complex-0.2.3.dist-info/RECORD
