Metadata-Version: 2.1
Name: keras-complex
Version: 0.2.3
Summary: Complex values in Keras
Maintainer-email: Jesper Dramsch <jesper@dramsch.net>
License: Tensorflow Port: MIT License
Project-URL: homepage, https://github.com/JesperDramsch/keras-complex/
Project-URL: documentation, https://keras-complex.readthedocs.org
Project-URL: repository, https://github.com/JesperDramsch/keras-complex
Project-URL: changelog, https://github.com/JesperDramsch/keras-complex/releases
Project-URL: bugtracker, https://github.com/JesperDramsch/keras-complex/issues
Keywords: Machine Learning,Deep Learning,Complex Numbers,Keras,TensorFlow
Classifier: Development Status :: 3 - Alpha
Classifier: Intended Audience :: Education
Classifier: Intended Audience :: Science/Research
Classifier: License :: OSI Approved :: MIT License
Classifier: Programming Language :: Python :: 3 :: Only
Classifier: Programming Language :: Python :: 3
Classifier: Programming Language :: Python :: 3.8
Classifier: Programming Language :: Python :: 3.9
Classifier: Programming Language :: Python :: 3.10
Classifier: Topic :: Software Development :: Libraries
Classifier: Topic :: Software Development :: Libraries :: Python Modules
Classifier: Topic :: Scientific/Engineering :: Artificial Intelligence
Classifier: Topic :: Scientific/Engineering :: Mathematics
Classifier: Topic :: Documentation :: Sphinx
Classifier: Natural Language :: English
Requires-Python: >=3.8
License-File: LICENSE.md
Requires-Dist: tensorflow (>="2.0.0")
Requires-Dist: numpy
Requires-Dist: scipy
Requires-Dist: scikit-learn
